MANIFEST.in
README.txt
setup.cfg
setup.py
doc/notas.txt
src/examples/TEST/run.py
src/examples/TEST/srv/dir_html.py
src/examples/TEST/srv/index_html.py
src/examples/TEST/srv/test_html.py
src/examples/TEST/srv/data/tree_json.py
src/examples/TEST/srv/dojo/alert_html.py
src/examples/TEST/srv/dojo/index_html.py
src/examples/TEST/srv/dojo/panels_html.py
src/examples/TEST/srv/dojo/dijit/tree_parent_html.py
src/examples/TEST/srv/pyojo/README.txt
src/examples/TEST/srv/pyojo/base_js.py
src/examples/TEST/srv/pyojo/boot_js.py
src/examples/TEST/srv/pyojo/gui_js.py
src/examples/TEST/srv/pyojo/gui_tree_js.py
src/examples/TEST/srv/pyojo/data/tree_nav_js.py
src/examples/testing/XML_responses.py
src/examples/testing/command.py
src/examples/testing/app/__init__.py
src/examples/testing/app/call/base.py
src/examples/testing/app/call/boot.py
src/examples/testing/app/call/gui.py
src/examples/testing/app/call/ready.py
src/examples/testing/app/call/testing.py
src/examples/use/basic_hello.py
src/examples/use/route_match.py
src/examples/use/routes.py
src/pyojo/TODO.txt
src/pyojo/__init__.py
src/pyojo/all.py
src/pyojo/base.py
src/pyojo/config.ini
src/pyojo/content.py
src/pyojo/data.py
src/pyojo/func.py
src/pyojo/util.py
src/pyojo.egg-info/PKG-INFO
src/pyojo/app/__init__.py
src/pyojo/doc/Makefile
src/pyojo/doc/build.log
src/pyojo/doc/build.rst
src/pyojo/doc/conf.py
src/pyojo/doc/go.bat
src/pyojo/doc/index.txt
src/pyojo/doc/make.bat
src/pyojo/doc/toctree.txt
src/pyojo/doc/ext/__init__.py
src/pyojo/doc/ext/sphinx_mod.py
src/pyojo/doc/ext/autosummary/__init__.py
src/pyojo/doc/ext/autosummary/generate.py
src/pyojo/doc/ext/static/favicon.ico
src/pyojo/doc/ext/templates/base.rst
src/pyojo/doc/ext/templates/class.rst
src/pyojo/doc/ext/templates/decorator.rst
src/pyojo/doc/ext/templates/exception.rst
src/pyojo/doc/ext/templates/function.rst
src/pyojo/doc/ext/templates/module.rst
src/pyojo/doc/ext/templates/package.rst
src/pyojo/js/__init__.py
src/pyojo/js/code.py
src/pyojo/js/utils.py
src/pyojo/js/dijit/__init__.py
