Metadata-Version: 1.0
Name: pyojo
Version: 0.0.2
Summary:  Web framework to create Dojo apps.
Home-page: http://www.pyojo.com
Author: Txema Vicente
Author-email: txema@nabla.net
License: BSD
Keywords: WSGI dojo
Platform: UNKNOWN
Classifier: Development Status :: 1 - Planning
Classifier: Intended Audience :: Developers
Classifier: Operating System :: OS Independent
Classifier: Topic :: Software Development :: Libraries :: Python Modules
Classifier: Topic :: Internet :: WWW/HTTP :: WSGI :: Application
Classifier: License :: OSI Approved :: BSD License
